robotcloud/__init__.py
robotcloud/api.py
robotcloud/authenticator.py
robotcloud/constants.py
robotcloud/exceptions.py
robotcloud/typing.py
robotcloud/endpoints/__init__.py
robotcloud/endpoints/applications.py
robotcloud/endpoints/configurationtypes.py
robotcloud/endpoints/devices.py
robotcloud/endpoints/locations.py
robotcloud/endpoints/login.py
robotcloud/endpoints/organizations.py
robotcloud/endpoints/projects.py
robotcloud/endpoints/services.py
robotcloud/endpoints/services_classifiers.py
robotcloud/endpoints/services_data.py
robotcloud/endpoints/subsystems.py
robotcloud/endpoints/tags.py
robotcloud/endpoints/users.py
robotcloud/endpoints/endpoint_classes/__init__.py
robotcloud/endpoints/endpoint_classes/services_data.py
robotcloud/utils/__init__.py
robotcloud/utils/paginated_response.py
robotcloud/utils/pagination.py
robotcloud/utils/datatables/__init__.py
robotcloud/utils/datatables/request.py
robotcloud/utils/datatables/response.py
robotcloud_client-0.1.0.dist-info/METADATA
robotcloud_client-0.1.0.dist-info/WHEEL
robotcloud_client-0.1.0.dist-info/top_level.txt
robotcloud_client-0.1.0.dist-info/RECORD
