Metadata-Version: 2.1
Name: robotcloud-client
Version: 0.1.0
Summary: Client to interact with robotcloud API from a python project.
Home-page: https://github.com/robotmallorca/sw.module.python.robotcloud.client
Author: Bernat Galmés Rubert
Author-email: bernat.galmes@robotbas.com
Keywords: client,robotcloud
Requires-Python: >=3.8.0
Requires-Dist: requests>=2.28
